{
  "version": "CV304_MARKET_SCANNER",
  "status": "warning",
  "startedAt": "2026-06-19 22:57:05",
  "updatedAt": "2026-06-20 00:49:59",
  "baseDate": "20260619",
  "source": "naver_market_sum_universe_v304",
  "universeTargetTopNByTradingValue": 1200,
  "universeCount": 1200,
  "scannedCount": 1132,
  "selectedInputCount": 120,
  "errorCount": 69,
  "gradeCounts": {
    "S": 69,
    "A": 51
  },
  "sectorCounts": {
    "반도체·AI": 8,
    "원전·전력·에너지": 1,
    "금융·밸류업": 5,
    "KOSPI 자동선별": 85,
    "조선·해양": 2,
    "KOSDAQ 자동선별": 18,
    "자동차·모빌리티": 1
  },
  "outputs": [
    "stock_candidates_input.csv",
    "market_universe.json",
    "market_scan_results.json",
    "market_scanner_summary.json",
    "market_scanner_errors.txt"
  ]
}