{
  "version": "CV306_EOD_MINIMAL_SCANNER",
  "mode": "EOD_CLOSE_BASED",
  "status": "ok",
  "startedAt": "2026-07-08 19:48:33",
  "updatedAt": "2026-07-08 19:48:47",
  "strategyDate": "2026-07-08",
  "source": "naver_market_sum_v306_eod_minimal",
  "maxPagesPerMarket": 8,
  "universeTargetTopN": 300,
  "universeCount": 300,
  "deepScanCount": 0,
  "selectedInputCount": 80,
  "errorCount": 0,
  "elapsedSeconds": 13.5,
  "gradeCounts": {
    "A": 21,
    "B": 51,
    "S": 1,
    "C": 7
  },
  "sectorCounts": {
    "반도체·AI": 4,
    "KOSPI 종가선별": 48,
    "자동차·모빌리티": 3,
    "금융·밸류업": 3,
    "원전·전력·에너지": 4,
    "조선·해양": 4,
    "KOSDAQ 종가선별": 5,
    "2차전지·소재": 4,
    "인터넷·게임·콘텐츠": 1,
    "방산·우주항공": 2,
    "바이오·제약": 2
  },
  "outputs": [
    "stock_candidates_input.csv",
    "market_universe.json",
    "market_scan_results.json",
    "market_scanner_summary.json",
    "market_scanner_errors.txt"
  ]
}