{
  "version": "V312_ALL_STOCK_LOOKUP_INDEX",
  "status": "ok",
  "updatedAt": "2026-06-11 03:40:38 KST",
  "stockCount": 2529,
  "recommendedCount": 40,
  "marketCounts": {
    "KOSPI": 843,
    "KOSDAQ": 1686
  },
  "krxKindCount": 0,
  "naverMarketSumCount": 2529,
  "outputFiles": [
    "stock_lookup_index.json",
    "stock_lookup_compact.json",
    "v312_all_stock_lookup_report.json"
  ],
  "topRecommended": [
    {
      "rank": 1,
      "name": "카카오뱅크",
      "code": "323410",
      "score": 73
    },
    {
      "rank": 2,
      "name": "피에스케이",
      "code": "319660",
      "score": 71
    },
    {
      "rank": 3,
      "name": "테크윙",
      "code": "089030",
      "score": 70
    },
    {
      "rank": 4,
      "name": "피에스케이홀딩스",
      "code": "031980",
      "score": 70
    },
    {
      "rank": 5,
      "name": "엘티씨",
      "code": "170920",
      "score": 69
    },
    {
      "rank": 6,
      "name": "로보스타",
      "code": "090360",
      "score": 69
    },
    {
      "rank": 7,
      "name": "더블유게임즈",
      "code": "192080",
      "score": 69
    },
    {
      "rank": 8,
      "name": "후성",
      "code": "093370",
      "score": 68
    },
    {
      "rank": 9,
      "name": "유진테크",
      "code": "084370",
      "score": 68
    },
    {
      "rank": 10,
      "name": "현대해상",
      "code": "001450",
      "score": 68
    }
  ]
}