[
  {
    "code": "042660",
    "name": "한화오션",
    "market": "KOSPI",
    "sector": "조선/방산",
    "score": 91,
    "grade": "B+",
    "currentPrice": 128700,
    "close": 128700,
    "reason": "한화오션 A246 목표가 정제 후보",
    "chartScore": 0,
    "supplyScore": 0,
    "newsScore": 0,
    "fundamentalScore": 0,
    "riskScore": 0,
    "targetMedianPrice": 170316,
    "realisticTargetPrice": 136500,
    "observeTimingPrice": 119000,
    "stopTimingPrice": 102000,
    "reportTargetCount": 1,
    "reportTargetPricesText": "170,316원",
    "reportTargetReason": "네이버 컨센서스 목표가 170,316원 기준. 현재가 128,700원 대비 상승여력 32.3%. 현실목표 136,500원(80%), 관찰 119,000원(70%), 목표가 기준 손절 102,000원(60%).",
    "targetEngineVersion": "A253",
    "updatedAt": "2026-06-19T20:53:45",
    "targetUpsidePercent": 32.3,
    "targetPriceSourceLabel": "네이버 컨센서스 목표가",
    "chartStopPrice": 118500,
    "chartStopReason": "차트 기준 손절선: 검증 현재가 128,700원 기준 약 -8% 구간 118,500원.",
    "stopGuideReason": "중장기 손절은 목표가 기준 102,000원, 단기 손절은 차트 기준 118,500원입니다. 단기 매매는 차트 손절 우선, 중장기 보유는 목표가 기준 손절을 참고합니다.",
    "priceValidationStatus": "정상",
    "priceValidationReason": "한화오션 현재가 128,700원은 검증 범위 내."
  },
  {
    "code": "329180",
    "name": "HD현대중공업",
    "market": "KOSPI",
    "sector": "조선",
    "score": 90,
    "grade": "B+",
    "currentPrice": 300000,
    "close": 300000,
    "reason": "HD현대중공업 A246 목표가 정제 후보",
    "chartScore": 0,
    "supplyScore": 0,
    "newsScore": 0,
    "fundamentalScore": 0,
    "riskScore": 0,
    "targetMedianPrice": 0,
    "realisticTargetPrice": 0,
    "observeTimingPrice": 0,
    "stopTimingPrice": 0,
    "reportTargetCount": 0,
    "reportTargetPricesText": "",
    "reportTargetReason": "정제 후 유효 목표주가 없음.",
    "targetEngineVersion": "A253",
    "updatedAt": "2026-06-19T20:53:45",
    "chartStopPrice": 276000,
    "chartStopReason": "차트 기준 손절선: 검증 현재가 300,000원 기준 약 -8% 구간 276,000원.",
    "stopGuideReason": "중장기 손절은 목표가 기준 0원, 단기 손절은 차트 기준 276,000원입니다. 단기 매매는 차트 손절 우선, 중장기 보유는 목표가 기준 손절을 참고합니다.",
    "priceValidationStatus": "정상",
    "priceValidationReason": "HD현대중공업 현재가 300,000원은 검증 범위 내."
  },
  {
    "code": "034020",
    "name": "두산에너빌리티",
    "market": "KOSPI",
    "sector": "원전/에너지",
    "score": 89,
    "grade": "B+",
    "currentPrice": 105250,
    "close": 105250,
    "reason": "두산에너빌리티 A246 목표가 정제 후보",
    "chartScore": 0,
    "supplyScore": 0,
    "newsScore": 0,
    "fundamentalScore": 0,
    "riskScore": 0,
    "targetMedianPrice": 149563,
    "realisticTargetPrice": 119500,
    "observeTimingPrice": 104500,
    "stopTimingPrice": 89700,
    "reportTargetCount": 1,
    "reportTargetPricesText": "149,563원",
    "reportTargetReason": "네이버 컨센서스 목표가 149,563원 기준. 현재가 105,250원 대비 상승여력 42.1%. 현실목표 119,500원(80%), 관찰 104,500원(70%), 목표가 기준 손절 89,700원(60%).",
    "targetEngineVersion": "A253",
    "updatedAt": "2026-06-19T20:53:45",
    "targetUpsidePercent": 42.1,
    "targetPriceSourceLabel": "네이버 컨센서스 목표가",
    "chartStopPrice": 96800,
    "chartStopReason": "차트 기준 손절선: 검증 현재가 105,250원 기준 약 -8% 구간 96,800원.",
    "stopGuideReason": "중장기 손절은 목표가 기준 89,700원, 단기 손절은 차트 기준 96,800원입니다. 단기 매매는 차트 손절 우선, 중장기 보유는 목표가 기준 손절을 참고합니다.",
    "priceValidationStatus": "정상",
    "priceValidationReason": "두산에너빌리티 현재가 105,250원은 검증 범위 내."
  },
  {
    "code": "272210",
    "name": "한화시스템",
    "market": "KOSPI",
    "sector": "방산",
    "score": 88,
    "grade": "B+",
    "currentPrice": 132671,
    "close": 132671,
    "reason": "한화시스템 A246 목표가 정제 후보",
    "chartScore": 0,
    "supplyScore": 0,
    "newsScore": 0,
    "fundamentalScore": 0,
    "riskScore": 0,
    "targetMedianPrice": 148231,
    "realisticTargetPrice": 118500,
    "observeTimingPrice": 104000,
    "stopTimingPrice": 88900,
    "reportTargetCount": 1,
    "reportTargetPricesText": "148,231원",
    "reportTargetReason": "네이버 컨센서스 목표가 148,231원 기준. 현재가 132,671원 대비 상승여력 11.7%. 현실목표 118,500원(80%), 관찰 104,000원(70%), 목표가 기준 손절 88,900원(60%).",
    "targetEngineVersion": "A253",
    "updatedAt": "2026-06-19T20:53:45",
    "targetUpsidePercent": 11.7,
    "targetPriceSourceLabel": "네이버 컨센서스 목표가",
    "chartStopPrice": 122000,
    "chartStopReason": "차트 기준 손절선: 검증 현재가 132,671원 기준 약 -8% 구간 122,000원.",
    "stopGuideReason": "중장기 손절은 목표가 기준 88,900원, 단기 손절은 차트 기준 122,000원입니다. 단기 매매는 차트 손절 우선, 중장기 보유는 목표가 기준 손절을 참고합니다.",
    "priceValidationStatus": "정상",
    "priceValidationReason": "한화시스템 현재가 132,671원은 검증 범위 내."
  },
  {
    "code": "005930",
    "name": "삼성전자",
    "market": "KOSPI",
    "sector": "반도체",
    "score": 87,
    "grade": "B+",
    "currentPrice": 0,
    "close": 0,
    "reason": "삼성전자 A246 목표가 정제 후보",
    "chartScore": 0,
    "supplyScore": 0,
    "newsScore": 0,
    "fundamentalScore": 0,
    "riskScore": 0,
    "targetMedianPrice": 0,
    "realisticTargetPrice": 0,
    "observeTimingPrice": 0,
    "stopTimingPrice": 0,
    "reportTargetCount": 0,
    "reportTargetPricesText": "",
    "reportTargetReason": "삼성전자 목표가는 현재가 대비 비정상 범위로 검증 제외.",
    "targetEngineVersion": "A253",
    "updatedAt": "2026-06-19T20:53:45",
    "targetUpsidePercent": 0.0,
    "targetPriceSourceLabel": "네이버 컨센서스 목표가",
    "chartStopPrice": 273500,
    "chartStopReason": "차트 기준 손절선: 273,500원. 단기 매매에서는 이 기준을 우선 확인합니다.",
    "stopGuideReason": "중장기 손절은 목표가 기준 275,000원, 단기 손절은 차트 기준 273,500원입니다. 단기 매매는 차트 손절 우선, 중장기 보유는 목표가 기준 손절을 참고합니다.",
    "priceValidationStatus": "검증필요",
    "priceValidationReason": "삼성전자 현재가 297,500원은 종목별 정상 범위를 벗어나 검증 필요."
  },
  {
    "code": "000660",
    "name": "SK하이닉스",
    "market": "KOSPI",
    "sector": "반도체",
    "score": 86,
    "grade": "B+",
    "currentPrice": 220000,
    "close": 220000,
    "reason": "SK하이닉스 A246 목표가 정제 후보",
    "chartScore": 0,
    "supplyScore": 0,
    "newsScore": 0,
    "fundamentalScore": 0,
    "riskScore": 0,
    "targetMedianPrice": 0,
    "realisticTargetPrice": 0,
    "observeTimingPrice": 0,
    "stopTimingPrice": 0,
    "reportTargetCount": 0,
    "reportTargetPricesText": "",
    "reportTargetReason": "정제 후 유효 목표주가 없음.",
    "targetEngineVersion": "A253",
    "updatedAt": "2026-06-19T20:53:45",
    "chartStopPrice": 202500,
    "chartStopReason": "차트 기준 손절선: 검증 현재가 220,000원 기준 약 -8% 구간 202,500원.",
    "stopGuideReason": "중장기 손절은 목표가 기준 0원, 단기 손절은 차트 기준 202,500원입니다. 단기 매매는 차트 손절 우선, 중장기 보유는 목표가 기준 손절을 참고합니다.",
    "priceValidationStatus": "정상",
    "priceValidationReason": "SK하이닉스 현재가 220,000원은 검증 범위 내."
  },
  {
    "code": "047810",
    "name": "한국항공우주",
    "market": "KOSPI",
    "sector": "방산",
    "score": 84,
    "grade": "B+",
    "currentPrice": 70000,
    "close": 70000,
    "reason": "한국항공우주 A246 목표가 정제 후보",
    "chartScore": 0,
    "supplyScore": 0,
    "newsScore": 0,
    "fundamentalScore": 0,
    "riskScore": 0,
    "targetMedianPrice": 128000,
    "realisticTargetPrice": 102500,
    "observeTimingPrice": 89600,
    "stopTimingPrice": 76800,
    "reportTargetCount": 1,
    "reportTargetPricesText": "128,000원",
    "reportTargetReason": "네이버 컨센서스 목표가 128,000원 기준. 현재가 70,000원 대비 상승여력 82.9%. 현실목표 102,500원(80%), 관찰 89,600원(70%), 목표가 기준 손절 76,800원(60%).",
    "targetEngineVersion": "A253",
    "updatedAt": "2026-06-19T20:53:45",
    "targetPriceSourceLabel": "네이버 컨센서스 목표가",
    "targetUpsidePercent": 82.9,
    "chartStopPrice": 64400,
    "chartStopReason": "차트 기준 손절선: 검증 현재가 70,000원 기준 약 -8% 구간 64,400원.",
    "stopGuideReason": "중장기 손절은 목표가 기준 76,800원, 단기 손절은 차트 기준 64,400원입니다. 단기 매매는 차트 손절 우선, 중장기 보유는 목표가 기준 손절을 참고합니다.",
    "priceValidationStatus": "정상",
    "priceValidationReason": "한국항공우주 현재가 70,000원은 검증 범위 내."
  },
  {
    "code": "241560",
    "name": "두산밥캣",
    "market": "KOSPI",
    "sector": "기계",
    "score": 82,
    "grade": "B+",
    "currentPrice": 55000,
    "close": 55000,
    "reason": "두산밥캣 A246 목표가 정제 후보",
    "chartScore": 0,
    "supplyScore": 0,
    "newsScore": 0,
    "fundamentalScore": 0,
    "riskScore": 0,
    "targetMedianPrice": 91071,
    "realisticTargetPrice": 72900,
    "observeTimingPrice": 63700,
    "stopTimingPrice": 54600,
    "reportTargetCount": 1,
    "reportTargetPricesText": "91,071원",
    "reportTargetReason": "네이버 컨센서스 목표가 91,071원 기준. 현재가 55,000원 대비 상승여력 65.6%. 현실목표 72,900원(80%), 관찰 63,700원(70%), 목표가 기준 손절 54,600원(60%).",
    "targetEngineVersion": "A253",
    "updatedAt": "2026-06-19T20:53:45",
    "targetUpsidePercent": 65.6,
    "targetPriceSourceLabel": "네이버 컨센서스 목표가",
    "chartStopPrice": 50600,
    "chartStopReason": "차트 기준 손절선: 검증 현재가 55,000원 기준 약 -8% 구간 50,600원.",
    "stopGuideReason": "중장기 손절은 목표가 기준 54,600원, 단기 손절은 차트 기준 50,600원입니다. 단기 매매는 차트 손절 우선, 중장기 보유는 목표가 기준 손절을 참고합니다.",
    "priceValidationStatus": "정상",
    "priceValidationReason": "두산밥캣 현재가 55,000원은 검증 범위 내."
  },
  {
    "code": "005380",
    "name": "현대차",
    "market": "KOSPI",
    "sector": "자동차",
    "score": 82,
    "grade": "B+",
    "currentPrice": 250000,
    "close": 250000,
    "reason": "현대차 A246 목표가 정제 후보",
    "chartScore": 0,
    "supplyScore": 0,
    "newsScore": 0,
    "fundamentalScore": 0,
    "riskScore": 0,
    "targetMedianPrice": 0,
    "realisticTargetPrice": 0,
    "observeTimingPrice": 0,
    "stopTimingPrice": 0,
    "reportTargetCount": 0,
    "reportTargetPricesText": "",
    "reportTargetReason": "정제 후 유효 목표주가 없음.",
    "targetEngineVersion": "A253",
    "updatedAt": "2026-06-19T20:53:45",
    "chartStopPrice": 230000,
    "chartStopReason": "차트 기준 손절선: 검증 현재가 250,000원 기준 약 -8% 구간 230,000원.",
    "stopGuideReason": "중장기 손절은 목표가 기준 0원, 단기 손절은 차트 기준 230,000원입니다. 단기 매매는 차트 손절 우선, 중장기 보유는 목표가 기준 손절을 참고합니다.",
    "priceValidationStatus": "정상",
    "priceValidationReason": "현대차 현재가 250,000원은 검증 범위 내."
  },
  {
    "code": "000270",
    "name": "기아",
    "market": "KOSPI",
    "sector": "자동차",
    "score": 81,
    "grade": "B+",
    "currentPrice": 115000,
    "close": 115000,
    "reason": "기아 A246 목표가 정제 후보",
    "chartScore": 0,
    "supplyScore": 0,
    "newsScore": 0,
    "fundamentalScore": 0,
    "riskScore": 0,
    "targetMedianPrice": 230000,
    "realisticTargetPrice": 184000,
    "observeTimingPrice": 161000,
    "stopTimingPrice": 138000,
    "reportTargetCount": 1,
    "reportTargetPricesText": "230,000원",
    "reportTargetReason": "네이버 컨센서스 목표가 230,000원 기준. 현재가 115,000원 대비 상승여력 100.0%. 현실목표 184,000원(80%), 관찰 161,000원(70%), 목표가 기준 손절 138,000원(60%).",
    "targetEngineVersion": "A253",
    "updatedAt": "2026-06-19T20:53:45",
    "targetUpsidePercent": 100.0,
    "targetPriceSourceLabel": "네이버 컨센서스 목표가",
    "chartStopPrice": 106000,
    "chartStopReason": "차트 기준 손절선: 검증 현재가 115,000원 기준 약 -8% 구간 106,000원.",
    "stopGuideReason": "중장기 손절은 목표가 기준 138,000원, 단기 손절은 차트 기준 106,000원입니다. 단기 매매는 차트 손절 우선, 중장기 보유는 목표가 기준 손절을 참고합니다.",
    "priceValidationStatus": "정상",
    "priceValidationReason": "기아 현재가 115,000원은 검증 범위 내."
  },
  {
    "code": "105560",
    "name": "KB금융",
    "market": "KOSPI",
    "sector": "금융",
    "score": 80,
    "grade": "B+",
    "currentPrice": 172000,
    "close": 172000,
    "reason": "KB금융 A246 목표가 정제 후보",
    "chartScore": 0,
    "supplyScore": 0,
    "newsScore": 0,
    "fundamentalScore": 0,
    "riskScore": 0,
    "targetMedianPrice": 204632,
    "realisticTargetPrice": 163500,
    "observeTimingPrice": 143000,
    "stopTimingPrice": 123000,
    "reportTargetCount": 1,
    "reportTargetPricesText": "204,632원",
    "reportTargetReason": "네이버 컨센서스 목표가 204,632원 기준. 현재가 172,000원 대비 상승여력 19.0%. 현실목표 163,500원(80%), 관찰 143,000원(70%), 목표가 기준 손절 123,000원(60%).",
    "targetEngineVersion": "A253",
    "updatedAt": "2026-06-19T20:53:45",
    "targetUpsidePercent": 19.0,
    "targetPriceSourceLabel": "네이버 컨센서스 목표가",
    "chartStopPrice": 158000,
    "chartStopReason": "차트 기준 손절선: 검증 현재가 172,000원 기준 약 -8% 구간 158,000원.",
    "stopGuideReason": "중장기 손절은 목표가 기준 123,000원, 단기 손절은 차트 기준 158,000원입니다. 단기 매매는 차트 손절 우선, 중장기 보유는 목표가 기준 손절을 참고합니다.",
    "priceValidationStatus": "정상",
    "priceValidationReason": "KB금융 현재가 172,000원은 검증 범위 내."
  },
  {
    "code": "055550",
    "name": "신한지주",
    "market": "KOSPI",
    "sector": "금융",
    "score": 79,
    "grade": "B+",
    "currentPrice": 60000,
    "close": 60000,
    "reason": "신한지주 A246 목표가 정제 후보",
    "chartScore": 0,
    "supplyScore": 0,
    "newsScore": 0,
    "fundamentalScore": 0,
    "riskScore": 0,
    "targetMedianPrice": 128611,
    "realisticTargetPrice": 103000,
    "observeTimingPrice": 90000,
    "stopTimingPrice": 77200,
    "reportTargetCount": 1,
    "reportTargetPricesText": "128,611원",
    "reportTargetReason": "네이버 컨센서스 목표가 128,611원 기준. 현재가 60,000원 대비 상승여력 114.4%. 현실목표 103,000원(80%), 관찰 90,000원(70%), 목표가 기준 손절 77,200원(60%).",
    "targetEngineVersion": "A253",
    "updatedAt": "2026-06-19T20:53:45",
    "targetUpsidePercent": 114.4,
    "targetPriceSourceLabel": "네이버 컨센서스 목표가",
    "chartStopPrice": 55200,
    "chartStopReason": "차트 기준 손절선: 검증 현재가 60,000원 기준 약 -8% 구간 55,200원.",
    "stopGuideReason": "중장기 손절은 목표가 기준 77,200원, 단기 손절은 차트 기준 55,200원입니다. 단기 매매는 차트 손절 우선, 중장기 보유는 목표가 기준 손절을 참고합니다.",
    "priceValidationStatus": "정상",
    "priceValidationReason": "신한지주 현재가 60,000원은 검증 범위 내."
  },
  {
    "code": "086790",
    "name": "하나금융지주",
    "market": "KOSPI",
    "sector": "금융",
    "score": 79,
    "grade": "B+",
    "currentPrice": 70000,
    "close": 70000,
    "reason": "하나금융지주 A246 목표가 정제 후보",
    "chartScore": 0,
    "supplyScore": 0,
    "newsScore": 0,
    "fundamentalScore": 0,
    "riskScore": 0,
    "targetMedianPrice": 157211,
    "realisticTargetPrice": 126000,
    "observeTimingPrice": 110000,
    "stopTimingPrice": 94300,
    "reportTargetCount": 1,
    "reportTargetPricesText": "157,211원",
    "reportTargetReason": "네이버 컨센서스 목표가 157,211원 기준. 현재가 70,000원 대비 상승여력 124.6%. 현실목표 126,000원(80%), 관찰 110,000원(70%), 목표가 기준 손절 94,300원(60%).",
    "targetEngineVersion": "A253",
    "updatedAt": "2026-06-19T20:53:45",
    "targetUpsidePercent": 124.6,
    "targetPriceSourceLabel": "네이버 컨센서스 목표가",
    "chartStopPrice": 64400,
    "chartStopReason": "차트 기준 손절선: 검증 현재가 70,000원 기준 약 -8% 구간 64,400원.",
    "stopGuideReason": "중장기 손절은 목표가 기준 94,300원, 단기 손절은 차트 기준 64,400원입니다. 단기 매매는 차트 손절 우선, 중장기 보유는 목표가 기준 손절을 참고합니다.",
    "priceValidationStatus": "정상",
    "priceValidationReason": "하나금융지주 현재가 70,000원은 검증 범위 내."
  },
  {
    "code": "316140",
    "name": "우리금융지주",
    "market": "KOSPI",
    "sector": "금융",
    "score": 78,
    "grade": "B+",
    "currentPrice": 16000,
    "close": 16000,
    "reason": "우리금융지주 A246 목표가 정제 후보",
    "chartScore": 0,
    "supplyScore": 0,
    "newsScore": 0,
    "fundamentalScore": 0,
    "riskScore": 0,
    "targetMedianPrice": 44200,
    "realisticTargetPrice": 35400,
    "observeTimingPrice": 30900,
    "stopTimingPrice": 26500,
    "reportTargetCount": 1,
    "reportTargetPricesText": "44,200원",
    "reportTargetReason": "네이버 컨센서스 목표가 44,200원 기준. 현재가 16,000원 대비 상승여력 176.2%. 현실목표 35,400원(80%), 관찰 30,900원(70%), 목표가 기준 손절 26,500원(60%).",
    "targetEngineVersion": "A253",
    "updatedAt": "2026-06-19T20:53:45",
    "targetUpsidePercent": 176.2,
    "targetPriceSourceLabel": "네이버 컨센서스 목표가",
    "chartStopPrice": 14700,
    "chartStopReason": "차트 기준 손절선: 검증 현재가 16,000원 기준 약 -8% 구간 14,700원.",
    "stopGuideReason": "중장기 손절은 목표가 기준 26,500원, 단기 손절은 차트 기준 14,700원입니다. 단기 매매는 차트 손절 우선, 중장기 보유는 목표가 기준 손절을 참고합니다.",
    "priceValidationStatus": "정상",
    "priceValidationReason": "우리금융지주 현재가 16,000원은 검증 범위 내."
  },
  {
    "code": "035420",
    "name": "NAVER",
    "market": "KOSPI",
    "sector": "인터넷",
    "score": 78,
    "grade": "B+",
    "currentPrice": 220000,
    "close": 220000,
    "reason": "NAVER A246 목표가 정제 후보",
    "chartScore": 0,
    "supplyScore": 0,
    "newsScore": 0,
    "fundamentalScore": 0,
    "riskScore": 0,
    "targetMedianPrice": 329227,
    "realisticTargetPrice": 263500,
    "observeTimingPrice": 230500,
    "stopTimingPrice": 197500,
    "reportTargetCount": 1,
    "reportTargetPricesText": "329,227원",
    "reportTargetReason": "네이버 컨센서스 목표가 329,227원 기준. 현재가 220,000원 대비 상승여력 49.6%. 현실목표 263,500원(80%), 관찰 230,500원(70%), 목표가 기준 손절 197,500원(60%).",
    "targetEngineVersion": "A253",
    "updatedAt": "2026-06-19T20:53:45",
    "targetUpsidePercent": 49.6,
    "targetPriceSourceLabel": "네이버 컨센서스 목표가",
    "chartStopPrice": 202500,
    "chartStopReason": "차트 기준 손절선: 검증 현재가 220,000원 기준 약 -8% 구간 202,500원.",
    "stopGuideReason": "중장기 손절은 목표가 기준 197,500원, 단기 손절은 차트 기준 202,500원입니다. 단기 매매는 차트 손절 우선, 중장기 보유는 목표가 기준 손절을 참고합니다.",
    "priceValidationStatus": "정상",
    "priceValidationReason": "NAVER 현재가 220,000원은 검증 범위 내."
  },
  {
    "code": "035720",
    "name": "카카오",
    "market": "KOSPI",
    "sector": "인터넷",
    "score": 76,
    "grade": "B+",
    "currentPrice": 55000,
    "close": 55000,
    "reason": "카카오 A246 목표가 정제 후보",
    "chartScore": 0,
    "supplyScore": 0,
    "newsScore": 0,
    "fundamentalScore": 0,
    "riskScore": 0,
    "targetMedianPrice": 72053,
    "realisticTargetPrice": 57600,
    "observeTimingPrice": 50400,
    "stopTimingPrice": 43200,
    "reportTargetCount": 1,
    "reportTargetPricesText": "72,053원",
    "reportTargetReason": "네이버 컨센서스 목표가 72,053원 기준. 현재가 55,000원 대비 상승여력 31.0%. 현실목표 57,600원(80%), 관찰 50,400원(70%), 목표가 기준 손절 43,200원(60%).",
    "targetEngineVersion": "A253",
    "updatedAt": "2026-06-19T20:53:45",
    "targetUpsidePercent": 31.0,
    "targetPriceSourceLabel": "네이버 컨센서스 목표가",
    "chartStopPrice": 50600,
    "chartStopReason": "차트 기준 손절선: 검증 현재가 55,000원 기준 약 -8% 구간 50,600원.",
    "stopGuideReason": "중장기 손절은 목표가 기준 43,200원, 단기 손절은 차트 기준 50,600원입니다. 단기 매매는 차트 손절 우선, 중장기 보유는 목표가 기준 손절을 참고합니다.",
    "priceValidationStatus": "정상",
    "priceValidationReason": "카카오 현재가 55,000원은 검증 범위 내."
  },
  {
    "code": "033780",
    "name": "KT&G",
    "market": "KOSPI",
    "sector": "방어주",
    "score": 76,
    "grade": "B+",
    "currentPrice": 110000,
    "close": 110000,
    "reason": "KT&G A246 목표가 정제 후보",
    "chartScore": 0,
    "supplyScore": 0,
    "newsScore": 0,
    "fundamentalScore": 0,
    "riskScore": 0,
    "targetMedianPrice": 217692,
    "realisticTargetPrice": 174000,
    "observeTimingPrice": 152500,
    "stopTimingPrice": 130500,
    "reportTargetCount": 1,
    "reportTargetPricesText": "217,692원",
    "reportTargetReason": "네이버 컨센서스 목표가 217,692원 기준. 현재가 110,000원 대비 상승여력 97.9%. 현실목표 174,000원(80%), 관찰 152,500원(70%), 목표가 기준 손절 130,500원(60%).",
    "targetEngineVersion": "A253",
    "updatedAt": "2026-06-19T20:53:45",
    "targetUpsidePercent": 97.9,
    "targetPriceSourceLabel": "네이버 컨센서스 목표가",
    "chartStopPrice": 101000,
    "chartStopReason": "차트 기준 손절선: 검증 현재가 110,000원 기준 약 -8% 구간 101,000원.",
    "stopGuideReason": "중장기 손절은 목표가 기준 130,500원, 단기 손절은 차트 기준 101,000원입니다. 단기 매매는 차트 손절 우선, 중장기 보유는 목표가 기준 손절을 참고합니다.",
    "priceValidationStatus": "정상",
    "priceValidationReason": "KT&G 현재가 110,000원은 검증 범위 내."
  },
  {
    "code": "011200",
    "name": "HMM",
    "market": "KOSPI",
    "sector": "해운",
    "score": 75,
    "grade": "B+",
    "currentPrice": 22000,
    "close": 22000,
    "reason": "HMM A246 목표가 정제 후보",
    "chartScore": 0,
    "supplyScore": 0,
    "newsScore": 0,
    "fundamentalScore": 0,
    "riskScore": 0,
    "targetMedianPrice": 22300,
    "realisticTargetPrice": 17800,
    "observeTimingPrice": 15600,
    "stopTimingPrice": 13400,
    "reportTargetCount": 1,
    "reportTargetPricesText": "22,300원",
    "reportTargetReason": "네이버 컨센서스 목표가 22,300원 기준. 현재가 22,000원 대비 상승여력 1.4%. 현실목표 17,800원(80%), 관찰 15,600원(70%), 목표가 기준 손절 13,400원(60%).",
    "targetEngineVersion": "A253",
    "updatedAt": "2026-06-19T20:53:45",
    "targetUpsidePercent": 1.4,
    "targetPriceSourceLabel": "네이버 컨센서스 목표가",
    "chartStopPrice": 20200,
    "chartStopReason": "차트 기준 손절선: 검증 현재가 22,000원 기준 약 -8% 구간 20,200원.",
    "stopGuideReason": "중장기 손절은 목표가 기준 13,400원, 단기 손절은 차트 기준 20,200원입니다. 단기 매매는 차트 손절 우선, 중장기 보유는 목표가 기준 손절을 참고합니다.",
    "priceValidationStatus": "정상",
    "priceValidationReason": "HMM 현재가 22,000원은 검증 범위 내."
  },
  {
    "code": "008770",
    "name": "호텔신라",
    "market": "KOSPI",
    "sector": "소비/여행",
    "score": 74,
    "grade": "B+",
    "currentPrice": 50000,
    "close": 50000,
    "reason": "호텔신라 A246 목표가 정제 후보",
    "chartScore": 0,
    "supplyScore": 0,
    "newsScore": 0,
    "fundamentalScore": 0,
    "riskScore": 0,
    "targetMedianPrice": 82750,
    "realisticTargetPrice": 66200,
    "observeTimingPrice": 57900,
    "stopTimingPrice": 49600,
    "reportTargetCount": 1,
    "reportTargetPricesText": "82,750원",
    "reportTargetReason": "네이버 컨센서스 목표가 82,750원 기준. 현재가 50,000원 대비 상승여력 65.5%. 현실목표 66,200원(80%), 관찰 57,900원(70%), 목표가 기준 손절 49,600원(60%).",
    "targetEngineVersion": "A253",
    "updatedAt": "2026-06-19T20:53:45",
    "targetUpsidePercent": 65.5,
    "targetPriceSourceLabel": "네이버 컨센서스 목표가",
    "chartStopPrice": 46000,
    "chartStopReason": "차트 기준 손절선: 검증 현재가 50,000원 기준 약 -8% 구간 46,000원.",
    "stopGuideReason": "중장기 손절은 목표가 기준 49,600원, 단기 손절은 차트 기준 46,000원입니다. 단기 매매는 차트 손절 우선, 중장기 보유는 목표가 기준 손절을 참고합니다.",
    "priceValidationStatus": "정상",
    "priceValidationReason": "호텔신라 현재가 50,000원은 검증 범위 내."
  },
  {
    "code": "108490",
    "name": "로보티즈",
    "market": "KOSDAQ",
    "sector": "로봇",
    "score": 74,
    "grade": "B+",
    "currentPrice": 45000,
    "close": 45000,
    "reason": "로보티즈 A246 목표가 정제 후보",
    "chartScore": 0,
    "supplyScore": 0,
    "newsScore": 0,
    "fundamentalScore": 0,
    "riskScore": 0,
    "targetMedianPrice": 0,
    "realisticTargetPrice": 0,
    "observeTimingPrice": 0,
    "stopTimingPrice": 0,
    "reportTargetCount": 0,
    "reportTargetPricesText": "",
    "reportTargetReason": "정제 후 유효 목표주가 없음.",
    "targetEngineVersion": "A253",
    "updatedAt": "2026-06-19T20:53:45",
    "chartStopPrice": 41400,
    "chartStopReason": "차트 기준 손절선: 검증 현재가 45,000원 기준 약 -8% 구간 41,400원.",
    "stopGuideReason": "중장기 손절은 목표가 기준 0원, 단기 손절은 차트 기준 41,400원입니다. 단기 매매는 차트 손절 우선, 중장기 보유는 목표가 기준 손절을 참고합니다.",
    "priceValidationStatus": "정상",
    "priceValidationReason": "로보티즈 현재가 45,000원은 검증 범위 내."
  },
  {
    "code": "277810",
    "name": "레인보우로보틱스",
    "market": "KOSDAQ",
    "sector": "로봇",
    "score": 73,
    "grade": "B+",
    "currentPrice": 170000,
    "close": 170000,
    "reason": "레인보우로보틱스 A246 목표가 정제 후보",
    "chartScore": 0,
    "supplyScore": 0,
    "newsScore": 0,
    "fundamentalScore": 0,
    "riskScore": 0,
    "targetMedianPrice": 0,
    "realisticTargetPrice": 0,
    "observeTimingPrice": 0,
    "stopTimingPrice": 0,
    "reportTargetCount": 0,
    "reportTargetPricesText": "",
    "reportTargetReason": "정제 후 유효 목표주가 없음.",
    "targetEngineVersion": "A253",
    "updatedAt": "2026-06-19T20:53:45",
    "chartStopPrice": 156500,
    "chartStopReason": "차트 기준 손절선: 검증 현재가 170,000원 기준 약 -8% 구간 156,500원.",
    "stopGuideReason": "중장기 손절은 목표가 기준 0원, 단기 손절은 차트 기준 156,500원입니다. 단기 매매는 차트 손절 우선, 중장기 보유는 목표가 기준 손절을 참고합니다.",
    "priceValidationStatus": "정상",
    "priceValidationReason": "레인보우로보틱스 현재가 170,000원은 검증 범위 내."
  },
  {
    "code": "247540",
    "name": "에코프로비엠",
    "market": "KOSDAQ",
    "sector": "2차전지",
    "score": 72,
    "grade": "B+",
    "currentPrice": 130000,
    "close": 130000,
    "reason": "에코프로비엠 A246 목표가 정제 후보",
    "chartScore": 0,
    "supplyScore": 0,
    "newsScore": 0,
    "fundamentalScore": 0,
    "riskScore": 0,
    "targetMedianPrice": 252611,
    "realisticTargetPrice": 202000,
    "observeTimingPrice": 177000,
    "stopTimingPrice": 151500,
    "reportTargetCount": 1,
    "reportTargetPricesText": "252,611원",
    "reportTargetReason": "네이버 컨센서스 목표가 252,611원 기준. 현재가 130,000원 대비 상승여력 94.3%. 현실목표 202,000원(80%), 관찰 177,000원(70%), 목표가 기준 손절 151,500원(60%).",
    "targetEngineVersion": "A253",
    "updatedAt": "2026-06-19T20:53:45",
    "targetUpsidePercent": 94.3,
    "targetPriceSourceLabel": "네이버 컨센서스 목표가",
    "chartStopPrice": 119500,
    "chartStopReason": "차트 기준 손절선: 검증 현재가 130,000원 기준 약 -8% 구간 119,500원.",
    "stopGuideReason": "중장기 손절은 목표가 기준 151,500원, 단기 손절은 차트 기준 119,500원입니다. 단기 매매는 차트 손절 우선, 중장기 보유는 목표가 기준 손절을 참고합니다.",
    "priceValidationStatus": "정상",
    "priceValidationReason": "에코프로비엠 현재가 130,000원은 검증 범위 내."
  },
  {
    "code": "086520",
    "name": "에코프로",
    "market": "KOSDAQ",
    "sector": "2차전지",
    "score": 71,
    "grade": "B+",
    "currentPrice": 70000,
    "close": 70000,
    "reason": "에코프로 A246 목표가 정제 후보",
    "chartScore": 0,
    "supplyScore": 0,
    "newsScore": 0,
    "fundamentalScore": 0,
    "riskScore": 0,
    "targetMedianPrice": 0,
    "realisticTargetPrice": 0,
    "observeTimingPrice": 0,
    "stopTimingPrice": 0,
    "reportTargetCount": 0,
    "reportTargetPricesText": "",
    "reportTargetReason": "정제 후 유효 목표주가 없음.",
    "targetEngineVersion": "A253",
    "updatedAt": "2026-06-19T20:53:45",
    "chartStopPrice": 64400,
    "chartStopReason": "차트 기준 손절선: 검증 현재가 70,000원 기준 약 -8% 구간 64,400원.",
    "stopGuideReason": "중장기 손절은 목표가 기준 0원, 단기 손절은 차트 기준 64,400원입니다. 단기 매매는 차트 손절 우선, 중장기 보유는 목표가 기준 손절을 참고합니다.",
    "priceValidationStatus": "정상",
    "priceValidationReason": "에코프로 현재가 70,000원은 검증 범위 내."
  },
  {
    "code": "196170",
    "name": "알테오젠",
    "market": "KOSDAQ",
    "sector": "바이오",
    "score": 71,
    "grade": "B+",
    "currentPrice": 300000,
    "close": 300000,
    "reason": "알테오젠 A246 목표가 정제 후보",
    "chartScore": 0,
    "supplyScore": 0,
    "newsScore": 0,
    "fundamentalScore": 0,
    "riskScore": 0,
    "targetMedianPrice": 566667,
    "realisticTargetPrice": 453500,
    "observeTimingPrice": 396500,
    "stopTimingPrice": 340000,
    "reportTargetCount": 1,
    "reportTargetPricesText": "566,667원",
    "reportTargetReason": "네이버 컨센서스 목표가 566,667원 기준. 현재가 300,000원 대비 상승여력 88.9%. 현실목표 453,500원(80%), 관찰 396,500원(70%), 목표가 기준 손절 340,000원(60%).",
    "targetEngineVersion": "A253",
    "updatedAt": "2026-06-19T20:53:45",
    "targetUpsidePercent": 88.9,
    "targetPriceSourceLabel": "네이버 컨센서스 목표가",
    "chartStopPrice": 276000,
    "chartStopReason": "차트 기준 손절선: 검증 현재가 300,000원 기준 약 -8% 구간 276,000원.",
    "stopGuideReason": "중장기 손절은 목표가 기준 340,000원, 단기 손절은 차트 기준 276,000원입니다. 단기 매매는 차트 손절 우선, 중장기 보유는 목표가 기준 손절을 참고합니다.",
    "priceValidationStatus": "정상",
    "priceValidationReason": "알테오젠 현재가 300,000원은 검증 범위 내."
  },
  {
    "code": "039030",
    "name": "이오테크닉스",
    "market": "KOSDAQ",
    "sector": "반도체장비",
    "score": 70,
    "grade": "B+",
    "currentPrice": 180000,
    "close": 180000,
    "reason": "이오테크닉스 A246 목표가 정제 후보",
    "chartScore": 0,
    "supplyScore": 0,
    "newsScore": 0,
    "fundamentalScore": 0,
    "riskScore": 0,
    "targetMedianPrice": 0,
    "realisticTargetPrice": 0,
    "observeTimingPrice": 0,
    "stopTimingPrice": 0,
    "reportTargetCount": 0,
    "reportTargetPricesText": "",
    "reportTargetReason": "정제 후 유효 목표주가 없음.",
    "targetEngineVersion": "A253",
    "updatedAt": "2026-06-19T20:53:45",
    "chartStopPrice": 165500,
    "chartStopReason": "차트 기준 손절선: 검증 현재가 180,000원 기준 약 -8% 구간 165,500원.",
    "stopGuideReason": "중장기 손절은 목표가 기준 0원, 단기 손절은 차트 기준 165,500원입니다. 단기 매매는 차트 손절 우선, 중장기 보유는 목표가 기준 손절을 참고합니다.",
    "priceValidationStatus": "정상",
    "priceValidationReason": "이오테크닉스 현재가 180,000원은 검증 범위 내."
  }
]